msgraph_email/__init__.py
msgraph_email/backend.py
django_msgraph_email-1.0.0.dist-info/LICENSE
django_msgraph_email-1.0.0.dist-info/METADATA
django_msgraph_email-1.0.0.dist-info/WHEEL
django_msgraph_email-1.0.0.dist-info/top_level.txt
django_msgraph_email-1.0.0.dist-info/RECORD
