Metadata-Version: 2.2
Name: django-msgraph_email
Version: 1.0.0
Summary: A Microsoft Graph Email Backend for Django using msal.
Author-email: Kishan Kumar <kishank@gspc.int>, Thomas Tilak <thomasti@spc.int>
License: MIT License
Project-URL: Homepage, https://github.com/thhomas/django-msgraph_email
Project-URL: Repository, https://github.com/thhomas/django-msgraph_email
Project-URL: Issues, https://github.com/thhomas/django-msgraph_email/issues
Keywords: Django,Backend,EmailBackend,Microsoft Graph
Classifier: Framework :: Django
Classifier: Framework :: Django :: 4.2
Classifier: Framework :: Django :: 5.0
Classifier: Programming Language :: Python :: 3.9
Classifier: Programming Language :: Python :: 3.10
Classifier: Programming Language :: Python :: 3.11
Classifier: Programming Language :: Python :: 3.12
Requires-Python: >=3.9
License-File: LICENSE
Requires-Dist: msal
